fancall/__init__.py
fancall/agent/__init__.py
fancall/agent/worker.py
fancall/api/__init__.py
fancall/api/router.py
fancall/factories.py
fancall/models.py
fancall/persona.py
fancall/prompts.py
fancall/py.typed
fancall/repositories/__init__.py
fancall/repositories/live_room_repository.py
fancall/schemas.py
fancall/services/__init__.py
fancall/services/livekit_service.py
fancall/settings.py
fancall-0.3.0.dist-info/METADATA
fancall-0.3.0.dist-info/WHEEL
fancall-0.3.0.dist-info/RECORD
